{"FqdyAfZZO+u8JH0R/KI0EA==":"x-960x720.jpg","InWGz4OKM2KbwgZ3agA5VA==":"capture-654x303.png","75Lujn4uc+RxHzzde7KOCg==":"2-640x263.png","rPsKd1Sd6uxhwaTEb1MkXA==":"4-682x297.png","cfdf0B+tc1Ifudum/AuX4w==":"7-287x143.png","0JMA0AsFSkSBWGeVW8PLqg==":"5-717x158.png","WtIT/8S3Vn/iow738EsjSQ==":"9-676x140.png","o7R3jpsKQAd2I2IrNe0Vmg==":"88-267x114.png","4lg7oUfF6jWsNEgx5AWYtw==":"88-160x68.png","BCarNHFMESLhkwsoW90M3Q==":"o-101x160.png","80cIDp+xS+HFUgso09jeGw==":"cute-robots-collage-cartoon-doodle-border-decorative-1300x1390.jpg"}